{"_type":"export","__export_format":4,"__export_date":"2019-08-04T05:13:11.625Z","__export_source":"insomnia.desktop.app:v6.5.4","resources":[{"_id":"req_a884a8e061454e15b49e16271eb10bdf","authentication":{},"body":{},"created":1564886151259,"description":"","headers":[],"isPrivate":false,"metaSortKey":-1564886151259,"method":"GET","modified":1564893326874,"name":"index","parameters":[],"parentId":"wrk_d2bb58fd8fba49d9ac8d2962b5674834","settingDisableRenderRequestBody":false,"settingEncodeUrl":true,"settingRebuildPath":true,"settingSendCookies":true,"settingStoreCookies":true,"url":"http://localhost:3001/api/products","_type":"request"},{"_id":"wrk_d2bb58fd8fba49d9ac8d2962b5674834","created":1564877151475,"description":"","modified":1564886139278,"name":"NodeJS","parentId":null,"_type":"workspace"},{"_id":"req_219cab1cc7b34095a8b19b06bf49ae8a","authentication":{},"body":{"mimeType":"application/json","text":"{\n\t\"title\": \"React\",\n\t\"description\": \"dasdioasjdiw\",\n\t\"url\": \"teste\"\n}"},"created":1564888533862,"description":"","headers":[{"id":"pair_cc30e458968d4b308c29e049d5d8c8a2","name":"Content-Type","value":"application/json"}],"isPrivate":false,"metaSortKey":-1564886151209,"method":"POST","modified":1564888833877,"name":"Create","parameters":[],"parentId":"wrk_d2bb58fd8fba49d9ac8d2962b5674834","settingDisableRenderRequestBody":false,"settingEncodeUrl":true,"settingRebuildPath":true,"settingSendCookies":true,"settingStoreCookies":true,"url":"http://localhost:3001/api/products","_type":"request"},{"_id":"req_77a9161a35a74267a3c7b5da6e4e0aa9","authentication":{},"body":{"mimeType":"application/json","text":"{\n\t\"title\": \"Foi\"\n\t\n}"},"created":1564893222980,"description":"","headers":[{"id":"pair_cc30e458968d4b308c29e049d5d8c8a2","name":"Content-Type","value":"application/json"}],"isPrivate":false,"metaSortKey":-1564886151184,"method":"PUT","modified":1564893334225,"name":"Update","parameters":[],"parentId":"wrk_d2bb58fd8fba49d9ac8d2962b5674834","settingDisableRenderRequestBody":false,"settingEncodeUrl":true,"settingRebuildPath":true,"settingSendCookies":true,"settingStoreCookies":true,"url":"http://localhost:3001/api/products/5d45eafbe46a8a1fd7371083","_type":"request"},{"_id":"req_dd9fc9d8ec5e4e108ecbcf106dbf0560","authentication":{},"body":{"mimeType":"application/json","text":"{\n\t\"title\": \"React\",\n\t\"description\": \"dasdioasjdiw\",\n\t\"url\": \"teste\"\n}"},"created":1564892766140,"description":"","headers":[{"id":"pair_cc30e458968d4b308c29e049d5d8c8a2","name":"Content-Type","value":"application/json"}],"isPrivate":false,"metaSortKey":-1564886151159,"method":"GET","modified":1564892936039,"name":"Show","parameters":[],"parentId":"wrk_d2bb58fd8fba49d9ac8d2962b5674834","settingDisableRenderRequestBody":false,"settingEncodeUrl":true,"settingRebuildPath":true,"settingSendCookies":true,"settingStoreCookies":true,"url":"http://localhost:3001/api/products/5d464ff2f5da7f1f3fbc1aac","_type":"request"},{"_id":"req_73b0e723fc8b48479cfb8a22ae06176c","authentication":{},"body":{"mimeType":"application/json","text":"{\n\t\"title\": \"React\",\n\t\"description\": \"dasdioasjdiw\",\n\t\"url\": \"teste\"\n}"},"created":1564893444079,"description":"","headers":[{"id":"pair_cc30e458968d4b308c29e049d5d8c8a2","name":"Content-Type","value":"application/json"}],"isPrivate":false,"metaSortKey":-1564886151109,"method":"DELETE","modified":1564893508342,"name":"Delete","parameters":[],"parentId":"wrk_d2bb58fd8fba49d9ac8d2962b5674834","settingDisableRenderRequestBody":false,"settingEncodeUrl":true,"settingRebuildPath":true,"settingSendCookies":true,"settingStoreCookies":true,"url":"http://localhost:3001/api/products/5d45eb05e46a8a1fd7371084","_type":"request"},{"_id":"env_a1123aacfa9afd1d9e5c0dfbbc4bee77bbfa9b90","color":null,"created":1564877151550,"data":{},"dataPropertyOrder":null,"isPrivate":false,"metaSortKey":1564877151550,"modified":1564877151550,"name":"Base Environment","parentId":"wrk_d2bb58fd8fba49d9ac8d2962b5674834","_type":"environment"},{"_id":"jar_a1123aacfa9afd1d9e5c0dfbbc4bee77bbfa9b90","cookies":[],"created":1564877151554,"modified":1564877151554,"name":"Default Jar","parentId":"wrk_d2bb58fd8fba49d9ac8d2962b5674834","_type":"cookie_jar"}]}